pytest_allure_id2history/listener.py
pytest_allure_id2history/plugin.py
pytest_allure_id2history-0.1.2.dist-info/LICENSE
pytest_allure_id2history-0.1.2.dist-info/METADATA
pytest_allure_id2history-0.1.2.dist-info/WHEEL
pytest_allure_id2history-0.1.2.dist-info/entry_points.txt
pytest_allure_id2history-0.1.2.dist-info/top_level.txt
pytest_allure_id2history-0.1.2.dist-info/RECORD
