Metadata-Version: 2.1
Name: pytest-allure-id2history
Version: 0.1.2
Summary: Overwrite allure history id with testcase full name and testcase id if testcase has id, exclude parameters.
Author-email: pytest-allure-id2history <ryaningli@foxmail.com>
Maintainer-email: pytest-allure-id2history <ryaningli@foxmail.com>
License: 
Project-URL: Repository, https://github.com/Ryaningli/pytest-allure-id2history
Classifier: Framework :: Pytest
Classifier: Development Status :: 4 - Beta
Classifier: Intended Audience :: Developers
Classifier: Topic :: Software Development :: Testing
Classifier: Operating System :: OS Independent
Classifier: Programming Language :: Python
Classifier: Programming Language :: Python :: 3.8
Classifier: Programming Language :: Python :: 3.9
Classifier: Programming Language :: Python :: 3.10
Classifier: Programming Language :: Python :: 3.11
Classifier: Programming Language :: Python :: 3.12
Classifier: Programming Language :: Python :: 3 :: Only
Classifier: Programming Language :: Python :: Implementation :: CPython
Classifier: Programming Language :: Python :: Implementation :: PyPy
Classifier: License :: OSI Approved :: MIT License
Requires-Python: >=3.8
License-File: LICENSE
Requires-Dist: pytest >=6.2.0
Requires-Dist: allure-pytest >=2.4.0
